{
    "name": "USEPA/WEST",
    "organization": "usepa",
    "description": "",
    "version": "",
    "status": "Development",
    "permissions": {
        "usageType": "openSource",
        "licenses": [
            {
                "URL": "https://github.com/USEPA/WEST/blob/master/LICENSE.md"
            }
        ]
    },
    "homepageURL": "https://github.com/USEPA/WEST",
    "downloadURL": "https://github.com/USEPA/WEST/archive/master.zip",
    "disclaimerURL": "https://github.com/USEPA/WEST/blob/master/DISCLAIMER.md",
    "repositoryURL": "https://github.com/USEPA/WEST.git/",
    "vcs": "git",
    "laborHours": 0,
    "tags": [
        "usgs"
    ],
    "languages": [],
    "contact": {
        "name": "USEPA"
    },
    "date": {
        "created": "2022-03-29T17:29:17Z",
        "lastModified": "2022-04-07T16:11:34Z",
        "metadataLastUpdated": "2025-06-04T06:24:54.171Z"
    }
}