{
    "contact": {
        "email": "chan@lanl.gov"
    },
    "date": {
        "created": "2024-03-22",
        "metadataLastUpdated": "2024-03-22"
    },
    "description": "This code analyzes openly available, downscaled climate model output and counts days in a year that are available to conduct prescribed fire based on meteorological prescription data obtained from US land management agencies.",
    "laborHours": 0.0,
    "languages": [],
    "name": "Analysis of prescribed fire days in climate model output",
    "organization": "Los Alamos National Laboratory (LANL)",
    "permissions": {
        "exemptionText": null,
        "licenses": [
            {
                "URL": "https://api.github.com/licenses/mit",
                "name": "MIT"
            }
        ],
        "usageType": "openSource"
    },
    "repositoryURL": "https://github.com/ajonko/RxFire",
    "status": "Production",
    "tags": [
        "DOE CODE",
        "Los Alamos National Laboratory (LANL)"
    ],
    "vcs": "git"
}