{
    "contact": {
        "email": "dkrakowski@anl.gov"
    },
    "date": {
        "created": "2021-09-29",
        "metadataLastUpdated": "2021-09-29"
    },
    "description": "Software development kit and command-line interface to access and interact with the Argonne Discovery Cloud platform. Software code can be used to enable software developers to add their own integrates into their own software.",
    "laborHours": 0.0,
    "languages": [],
    "name": "ARGONNE DISCOVERY CLOUD SDK&CLI",
    "organization": "Argonne National Laboratory (ANL)",
    "permissions": {
        "exemptionText": null,
        "licenses": [
            {
                "URL": "https://api.github.com/licenses/apache-2.0",
                "name": "Apache-2.0"
            }
        ],
        "usageType": "openSource"
    },
    "repositoryURL": "https://github.com/AD-SDL/adc-rdm-sdk",
    "status": "Production",
    "tags": [
        "DOE CODE",
        "Argonne National Laboratory (ANL)"
    ],
    "vcs": "git"
}