{
    "contact": {
        "email": "stooksburys@osti.gov"
    },
    "date": {
        "created": "2020-09-17",
        "metadataLastUpdated": "2020-09-17"
    },
    "description": "A collection of utilities for working with AWE.",
    "laborHours": 30.4,
    "languages": [],
    "name": "awe_utils",
    "organization": "Office of Scientific and Technical Information (OSTI)",
    "permissions": {
        "exemptionText": null,
        "licenses": [
            {
                "URL": "https://api.github.com/licenses/mit",
                "name": "MIT"
            }
        ],
        "usageType": "openSource"
    },
    "repositoryURL": "https://github.com/kbaseattic/awe_utils",
    "status": "Development",
    "tags": [
        "DOE CODE",
        "Office of Scientific and Technical Information (OSTI)"
    ],
    "vcs": "git"
}