{
    "contact": {
        "email": "gelipauline@lbl.gov"
    },
    "date": {
        "created": "2021-04-23",
        "metadataLastUpdated": "2021-06-15"
    },
    "description": "The Empirical Roofline Tool (ERT) empirically determines the machine characteristics (CPU or GPU-accelerated) that are needed to generate the machine characteristics for the roofline model.",
    "laborHours": 0.0,
    "languages": [],
    "name": "Empirical Roofline Tool (ERT) v1.1.0",
    "organization": "Lawrence Berkeley National Laboratory (LBNL)",
    "permissions": {
        "exemptionText": null,
        "licenses": [
            {
                "URL": "https://api.github.com/licenses/bsd-3-clause",
                "name": "BSD-3-Clause"
            }
        ],
        "usageType": "openSource"
    },
    "repositoryURL": "https://bitbucket.org/berkeleylab/cs-roofline-toolkit",
    "status": "Production",
    "tags": [
        "DOE CODE",
        "Lawrence Berkeley National Laboratory (LBNL)"
    ],
    "version": "v1.1.0"
}