{
    "contact": {
        "email": "holdensanchez2@llnl.gov"
    },
    "date": {
        "created": "2018-07-17",
        "metadataLastUpdated": "2018-07-17"
    },
    "description": "GLVis website: This repo contains the GLVis website MkDocs sources.\n",
    "laborHours": 1672.0,
    "languages": [],
    "name": "GLVis/web",
    "organization": "Lawrence Livermore National Laboratory (LLNL)",
    "permissions": {
        "exemptionText": null,
        "licenses": [
            {
                "URL": "https://api.github.com/licenses/lgpl-2.1",
                "name": "LGPL-2.1"
            }
        ],
        "usageType": "openSource"
    },
    "repositoryURL": "https://github.com/GLVis/web",
    "status": "Development",
    "tags": [
        "DOE CODE",
        "Lawrence Livermore National Laboratory (LLNL)"
    ],
    "vcs": "git"
}