{
    "contact": {
        "email": "stooksburys@osti.gov"
    },
    "date": {
        "created": "2020-09-10",
        "metadataLastUpdated": "2020-09-10"
    },
    "description": "Save plain text, HTML documents, and files as output from a KBase app.",
    "laborHours": 1535.2,
    "languages": [],
    "name": "KBaseReport",
    "organization": "Office of Scientific and Technical Information (OSTI)",
    "permissions": {
        "exemptionText": null,
        "licenses": [
            {
                "URL": "https://api.github.com/licenses/mit",
                "name": "MIT"
            }
        ],
        "usageType": "openSource"
    },
    "repositoryURL": "https://github.com/kbaseapps/KBaseReport",
    "status": "Development",
    "tags": [
        "DOE CODE",
        "Office of Scientific and Technical Information (OSTI)"
    ],
    "vcs": "git"
}