{
    "contact": {
        "email": "christopher.kowalczyk@inl.gov"
    },
    "date": {
        "created": "2018-04-24",
        "metadataLastUpdated": "2023-03-15"
    },
    "description": "Mesoscale Atomistic Glue Program for Integrated Execution",
    "laborHours": 14333.6,
    "languages": [],
    "name": "magpie",
    "organization": "Idaho National Laboratory (INL)",
    "permissions": {
        "exemptionText": null,
        "licenses": [
            {
                "URL": "https://api.github.com/licenses/lgpl-2.1",
                "name": "LGPL-2.1"
            }
        ],
        "usageType": "openSource"
    },
    "repositoryURL": "https://github.com/idaholab/magpie",
    "status": "Production",
    "tags": [
        "DOE CODE",
        "Idaho National Laboratory (INL)"
    ],
    "vcs": "git"
}