{
    "contact": {
        "email": "stooksburys@osti.gov"
    },
    "date": {
        "created": "2020-09-17",
        "metadataLastUpdated": "2020-09-17"
    },
    "description": "This is the repository for \"MotifFinderGibbs\" developed by KBase. This is a KBase module generated by the KBase Software Development Kit (SDK).",
    "laborHours": 2243808.8,
    "languages": [],
    "name": "MotifFinderGibbs",
    "organization": "Office of Scientific and Technical Information (OSTI)",
    "permissions": {
        "exemptionText": null,
        "licenses": [
            {
                "URL": "https://api.github.com/licenses/mit",
                "name": "MIT"
            }
        ],
        "usageType": "openSource"
    },
    "repositoryURL": "https://github.com/kbasecollaborations/MotifFinderGibbs",
    "status": "Development",
    "tags": [
        "DOE CODE",
        "Office of Scientific and Technical Information (OSTI)"
    ],
    "vcs": "git"
}