{
    "contact": {
        "email": "stooksburys@osti.gov"
    },
    "date": {
        "created": "2020-09-14",
        "metadataLastUpdated": "2020-09-14"
    },
    "description": "This is the repository for \"sdk_ontology\" developed by KBase. ",
    "laborHours": 4788.0,
    "languages": [],
    "name": "sdk_ontology",
    "organization": "Office of Scientific and Technical Information (OSTI)",
    "permissions": {
        "exemptionText": null,
        "licenses": [
            {
                "URL": "https://api.github.com/licenses/mit",
                "name": "MIT"
            }
        ],
        "usageType": "openSource"
    },
    "repositoryURL": "https://github.com/kbaseapps/ontology_service",
    "status": "Development",
    "tags": [
        "DOE CODE",
        "Office of Scientific and Technical Information (OSTI)"
    ],
    "vcs": "git"
}