{
    "contact": {
        "email": "maggiel@slac.stanford.edu"
    },
    "date": {
        "created": "2022-08-17",
        "metadataLastUpdated": "2022-08-17"
    },
    "description": "Linux kernel source tree.",
    "laborHours": 0.0,
    "languages": [],
    "name": "slaclab/linux",
    "organization": "SLAC National Accelerator Laboratory (SLAC)",
    "permissions": {
        "exemptionText": null,
        "licenses": [
            {
                "URL": "https://github.com/slaclab/linux/blob/master/COPYING",
                "name": "Other"
            }
        ],
        "usageType": "openSource"
    },
    "repositoryURL": "https://github.com/slaclab/linux",
    "status": "Development",
    "tags": [
        "DOE CODE",
        "SLAC National Accelerator Laboratory (SLAC)"
    ],
    "vcs": "git"
}