{
    "contact": {
        "email": "copyrightadmin@sandia.gov"
    },
    "date": {
        "created": "2021-02-15",
        "metadataLastUpdated": "2021-05-18"
    },
    "description": "SAND2021-0624 O Watchr is a Jenkins plugin for tracking the performance of subroutines over many individual builds. It reads build-generated performance reports and displays the data contained in these performance reports as a series of graphs. Sandia National Laboratories is a multimission laboratory managed and operated by National Technology & Engineering Solutions of Sandia, LLC, a wholly owned subsidiary of Honeywell International Inc., for the U.S. Department of Energy\u2019s National Nuclear Security Administration under contract DE-NA0003525.",
    "laborHours": 0.0,
    "languages": [
        "Java",
        "JavaScript",
        "Java",
        "Java"
    ],
    "name": "Watchr 3.0.0",
    "organization": "Sandia National Laboratories (SNL)",
    "permissions": {
        "exemptionText": null,
        "licenses": [
            {
                "URL": "https://github.com/sandialabs/watchr-jenkins/blob/master/LICENSE",
                "name": "Other"
            }
        ],
        "usageType": "openSource"
    },
    "repositoryURL": "https://github.com/sandialabs/watchr-jenkins",
    "status": "Development",
    "tags": [
        "DOE CODE",
        "Sandia National Laboratories (SNL)"
    ],
    "vcs": "git",
    "version": "3.0.0"
}