{
    "contact": {
        "URL": "https://github.com/cisagov",
        "email": "do_not_email_just_use_github@dhs.gov"
    },
    "date": {
        "created": "2020-08-18",
        "lastModified": "2023-07-26"
    },
    "description": "No description available...",
    "downloadURL": "https://api.github.com/repos/cisagov/cset-analytics-ui/downloads",
    "homepageURL": "https://github.com/cisagov/cset-analytics-ui",
    "laborHours": 11631.2,
    "languages": [
        "TypeScript",
        "HTML",
        "SCSS",
        "Shell",
        "JavaScript",
        "Makefile",
        "Dockerfile"
    ],
    "name": "cset-analytics-ui",
    "organization": "Cybersecurity and Infrastructure Security Agency",
    "permissions": {
        "licenses": [
            {
                "URL": "https://api.github.com/licenses/cc0-1.0",
                "name": "CC0-1.0"
            }
        ],
        "usageType": "openSource"
    },
    "repositoryURL": "https://github.com/cisagov/cset-analytics-ui.git",
    "status": "Development",
    "tags": [
        "github"
    ],
    "vcs": "git"
}